WebinarRu/__init__.py
WebinarRu/base_api.py
WebinarRu/models.py
WebinarRu/webinar_api.py
webinarru-0.1.3.dist-info/LICENSE
webinarru-0.1.3.dist-info/METADATA
webinarru-0.1.3.dist-info/WHEEL
webinarru-0.1.3.dist-info/RECORD
