Metadata-Version: 2.1
Name: WebinarRu
Version: 0.1.3
Summary: Python client for webinar.ru (mts-link.ru) platform
Home-page: https://github.com/gulyaeve/WebinarRu
License: MIT
Keywords: webinar,mts-link,WebinarRu
Author: gulyaeve
Author-email: gulyaev.e@icloud.com
Requires-Python: >=3.11,<4.0
Classifier: License :: OSI Approved :: MIT License
Classifier: Operating System :: OS Independent
Classifier: Programming Language :: Python :: 3
Classifier: Programming Language :: Python :: 3.11
Classifier: Programming Language :: Python :: 3.12
Requires-Dist: aiohttp (>=3.9.3,<4.0.0)
Requires-Dist: pydantic (>=2.5.3,<3.0.0)
Project-URL: Repository, https://github.com/gulyaeve/WebinarRu
